<?xml version="1.0" encoding="utf-8"?>
<AchievementData xmlns:xsd="http://www.w3.org/2001/XMLSchema" xmlns:xsi="http://www.w3.org/2001/XMLSchema-instance">
  <actionType>Electrocuted</actionType>
  <achievementName>The shookt Adventurer</achievementName>
  <achievementDescription>You just got electrocuted for the first time! Don't worry this won't be your last muwahahaha</achievementDescription>
  <count>1</count>
  <achievementUniqueID>EE01</achievementUniqueID>
  <itemType>0</itemType>
  <itemCategory>0</itemCategory>
  <iconPath />
</AchievementData>